pp_api/pp_api.py
pp_api/serversocket.py
pp_api/tcpserver.py
pp_api-0.1.2.dist-info/METADATA
pp_api-0.1.2.dist-info/WHEEL
pp_api-0.1.2.dist-info/top_level.txt
pp_api-0.1.2.dist-info/RECORD
