Metadata-Version: 2.1
Name: pp-api
Version: 0.1.2
Summary: Testing packages by Papa
Author: Papa
Author-email: htunpa2aung@gmail.com
Requires-Dist: requests
Requires-Dist: flask
